core_model/__init__.py
core_model/app.py
core_model/dataset_manager.py
core_model/main.py
code_model_temp-0.1.0.dist-info/METADATA
code_model_temp-0.1.0.dist-info/WHEEL
code_model_temp-0.1.0.dist-info/entry_points.txt
code_model_temp-0.1.0.dist-info/top_level.txt
code_model_temp-0.1.0.dist-info/RECORD
