Metadata-Version: 2.4
Name: code_model_temp
Version: 0.1.0
Summary: LLM-driven data analysis system with Streamlit and MLflow
Author: Anurag Sharma
Requires-Dist: streamlit
Requires-Dist: pandas
Requires-Dist: numpy
Requires-Dist: seaborn
Requires-Dist: scipy
Requires-Dist: scikit-learn
Requires-Dist: mlflow
Requires-Dist: openai
Requires-Dist: statsmodels
Dynamic: author
Dynamic: requires-dist
Dynamic: summary
